cute_sway_recorder/__main__.py
cute_sway_recorder/common.py
cute_sway_recorder/config_area.py
cute_sway_recorder/group_file_dest.py
cute_sway_recorder/group_selection.py
cute_sway_recorder/main.py
cute_sway_recorder/select_screen.py
cute_sway_recorder-0.1.11.dist-info/METADATA
cute_sway_recorder-0.1.11.dist-info/WHEEL
cute_sway_recorder-0.1.11.dist-info/entry_points.txt
cute_sway_recorder-0.1.11.dist-info/RECORD
