Metadata-Version: 2.1
Name: cute-sway-recorder
Version: 0.1.11
Summary: A small graphical screen recorder for wl-roots, leveraging wf-recorder and slurp
Home-page: https://github.com/it-is-wednesday/cute-sway-recorder
License: GPL-3.0-or-later
Author: Maor Kadosh
Author-email: pypi@avocadosh.xyz
Requires-Python: >=3.8,<3.13
Classifier: License :: OSI Approved :: GNU General Public License v3 or later (GPLv3+)
Classifier: Programming Language :: Python :: 3
Classifier: Programming Language :: Python :: 3.8
Classifier: Programming Language :: Python :: 3.9
Classifier: Programming Language :: Python :: 3.10
Classifier: Programming Language :: Python :: 3.11
Requires-Dist: PySide6 (==6.*)
Project-URL: Repository, https://github.com/it-is-wednesday/cute-sway-recorder
